{
  "Nation_Stats": {
    "timestamp": 1760657077262,
    "originalFile": "CyberNations_SE_Nation_Stats_10162025510002.zip",
    "downloadTime": "2025-10-16T23:24:37.262Z"
  },
  "Aid_Stats": {
    "timestamp": 1760657077341,
    "originalFile": "CyberNations_SE_Aid_Stats_10162025520002.zip",
    "downloadTime": "2025-10-16T23:24:37.341Z"
  },
  "War_Stats": {
    "timestamp": 1760657077409,
    "originalFile": "CyberNations_SE_War_Stats_10162025525002.zip",
    "downloadTime": "2025-10-16T23:24:37.409Z"
  }
}