{
  "alliance_id": 10097,
  "alliance_name": "Non Grata",
  "nations": {
    "2621": {
      "ruler_name": "James",
      "nation_name": "TIEIXIAIS",
      "discord_handle": "",
      "has_dra": true,
      "slots": {
        "sendTech": 0,
        "sendCash": 0,
        "getTech": 0,
        "getCash": 0,
        "send_priority": 2,
        "receive_priority": 2
      },
      "current_stats": {
        "technology": "9,888.80",
        "infrastructure": "10,383.32",
        "strength": "100630.358"
      },
      "notes": ""
    },
    "12258": {
      "ruler_name": "Commissar Sendoa",
      "nation_name": "Cataduanes",
      "discord_handle": "",
      "has_dra": true,
      "notes": "",
      "slots": {
        "sendTech": 0,
        "sendCash": 0,
        "getTech": 0,
        "getCash": 0,
        "send_priority": 2,
        "receive_priority": 1
      },
      "current_stats": {
        "technology": "308.86",
        "infrastructure": "2,200.72",
        "strength": "11946.129"
      }
    },
    "22121": {
      "ruler_name": "spartan 84",
      "nation_name": "UNSC Reach",
      "discord_handle": "",
      "has_dra": true,
      "slots": {
        "sendTech": 0,
        "sendCash": 0,
        "getTech": 0,
        "getCash": 0,
        "send_priority": 2,
        "receive_priority": 2
      },
      "current_stats": {
        "technology": "10,150.20",
        "infrastructure": "14,708.15",
        "strength": "116167.078"
      },
      "notes": ""
    },
    "40650": {
      "ruler_name": "kerschbs",
      "nation_name": "indica",
      "discord_handle": "",
      "has_dra": true,
      "slots": {
        "sendTech": 0,
        "sendCash": 0,
        "getTech": 0,
        "getCash": 0,
        "send_priority": 2,
        "receive_priority": 2
      },
      "current_stats": {
        "technology": "8,737.28",
        "infrastructure": "11,822.23",
        "strength": "99316.723"
      },
      "notes": ""
    },
    "72766": {
      "ruler_name": "Gofastleft",
      "nation_name": "Racesteria",
      "discord_handle": "",
      "has_dra": false,
      "notes": "",
      "slots": {
        "sendTech": 0,
        "sendCash": 0,
        "getTech": 0,
        "getCash": 0,
        "send_priority": 2,
        "receive_priority": 2
      },
      "current_stats": {
        "technology": "9,630.79",
        "infrastructure": "6,990.97",
        "strength": "75746.989"
      }
    },
    "91872": {
      "ruler_name": "PuliSher",
      "nation_name": "Kerjälä",
      "discord_handle": "",
      "has_dra": true,
      "slots": {
        "sendTech": 0,
        "sendCash": 0,
        "getTech": 0,
        "getCash": 0,
        "send_priority": 2,
        "receive_priority": 2
      },
      "current_stats": {
        "technology": "501.68",
        "infrastructure": "2,544.08",
        "strength": "24017.101"
      },
      "notes": ""
    },
    "132232": {
      "ruler_name": "Justin666",
      "nation_name": "Pain nation 666",
      "discord_handle": "",
      "has_dra": false,
      "notes": "",
      "slots": {
        "sendTech": 0,
        "sendCash": 0,
        "getTech": 0,
        "getCash": 0,
        "send_priority": 2,
        "receive_priority": 2
      },
      "current_stats": {
        "technology": "13,452.27",
        "infrastructure": "15,011.36",
        "strength": "135325.306"
      }
    },
    "133051": {
      "ruler_name": "MikeTheFirst",
      "nation_name": "MikeLand",
      "discord_handle": "",
      "has_dra": false,
      "notes": "",
      "slots": {
        "sendTech": 0,
        "sendCash": 0,
        "getTech": 0,
        "getCash": 0,
        "send_priority": 2,
        "receive_priority": 2
      },
      "current_stats": {
        "technology": "9,404.29",
        "infrastructure": "12,999.75",
        "strength": "104820.425"
      }
    },
    "136993": {
      "ruler_name": "Hotti",
      "nation_name": "Kiosk",
      "discord_handle": "",
      "has_dra": false,
      "notes": "",
      "slots": {
        "sendTech": 0,
        "sendCash": 0,
        "getTech": 0,
        "getCash": 0,
        "send_priority": 3,
        "receive_priority": 3
      },
      "current_stats": {
        "technology": "400.19",
        "infrastructure": "9,999.99",
        "strength": "47685.913"
      }
    },
    "144192": {
      "ruler_name": "Sagha",
      "nation_name": "Nickelattia",
      "discord_handle": "",
      "has_dra": false,
      "notes": "",
      "slots": {
        "sendTech": 0,
        "sendCash": 0,
        "getTech": 0,
        "getCash": 0,
        "send_priority": 3,
        "receive_priority": 3
      },
      "current_stats": {
        "technology": "10,405.34",
        "infrastructure": "1,379.64",
        "strength": "60651.426"
      }
    },
    "155031": {
      "ruler_name": "joanne1",
      "nation_name": "Tweetypie",
      "discord_handle": "",
      "has_dra": false,
      "notes": "",
      "slots": {
        "sendTech": 0,
        "sendCash": 0,
        "getTech": 0,
        "getCash": 0,
        "send_priority": 3,
        "receive_priority": 3
      },
      "current_stats": {
        "technology": "9,508.60",
        "infrastructure": "16,999.99",
        "strength": "125059.811"
      }
    },
    "155817": {
      "ruler_name": "MutedFaith",
      "nation_name": "Faithoria",
      "discord_handle": "",
      "has_dra": true,
      "slots": {
        "sendTech": 0,
        "sendCash": 0,
        "getTech": 0,
        "getCash": 0,
        "send_priority": 2,
        "receive_priority": 2
      },
      "current_stats": {
        "technology": "8,537.17",
        "infrastructure": "12,391.90",
        "strength": "100268.44"
      },
      "notes": ""
    },
    "155826": {
      "ruler_name": "weebl2000",
      "nation_name": "Azeer",
      "discord_handle": "",
      "has_dra": true,
      "slots": {
        "sendTech": 0,
        "sendCash": 0,
        "getTech": 0,
        "getCash": 0,
        "send_priority": 2,
        "receive_priority": 2
      },
      "current_stats": {
        "technology": "6,716.75",
        "infrastructure": "12,373.48",
        "strength": "86609.194"
      },
      "notes": ""
    },
    "166207": {
      "ruler_name": "Jekalle",
      "nation_name": "Ranus",
      "discord_handle": "",
      "has_dra": true,
      "slots": {
        "sendTech": 0,
        "sendCash": 0,
        "getTech": 0,
        "getCash": 0,
        "send_priority": 2,
        "receive_priority": 2
      },
      "current_stats": {
        "technology": "6,634.30",
        "infrastructure": "6,999.99",
        "strength": "71347.626"
      },
      "notes": ""
    },
    "181481": {
      "ruler_name": "HammerMan",
      "nation_name": "Dooche",
      "discord_handle": "",
      "has_dra": false,
      "notes": "",
      "slots": {
        "sendTech": 0,
        "sendCash": 0,
        "getTech": 0,
        "getCash": 0,
        "send_priority": 2,
        "receive_priority": 2
      },
      "current_stats": {
        "technology": "132.45",
        "infrastructure": "9,413.05",
        "strength": "38952.951"
      }
    },
    "188637": {
      "ruler_name": "Caustic",
      "nation_name": "Hazardous Materials",
      "discord_handle": "",
      "has_dra": true,
      "slots": {
        "sendTech": 0,
        "sendCash": 0,
        "getTech": 0,
        "getCash": 0,
        "send_priority": 2,
        "receive_priority": 2
      },
      "current_stats": {
        "technology": "7,406.10",
        "infrastructure": "10,127.09",
        "strength": "77211.784"
      },
      "notes": ""
    },
    "189605": {
      "ruler_name": "Polemos",
      "nation_name": "Realm of Fury",
      "discord_handle": "",
      "has_dra": false,
      "notes": "",
      "slots": {
        "sendTech": 0,
        "sendCash": 0,
        "getTech": 0,
        "getCash": 0,
        "send_priority": 3,
        "receive_priority": 3
      },
      "current_stats": {
        "technology": "7,998.99",
        "infrastructure": "9,638.34",
        "strength": "81501.943"
      }
    },
    "230895": {
      "ruler_name": "TCTriangle",
      "nation_name": "Taninsania",
      "discord_handle": "",
      "has_dra": false,
      "notes": "",
      "slots": {
        "sendTech": 0,
        "sendCash": 0,
        "getTech": 0,
        "getCash": 0,
        "send_priority": 2,
        "receive_priority": 2
      },
      "current_stats": {
        "technology": "9,027.39",
        "infrastructure": "12,235.30",
        "strength": "104363.597"
      }
    },
    "234369": {
      "ruler_name": "EaTeMuP",
      "nation_name": "EatemVille",
      "discord_handle": "",
      "has_dra": true,
      "slots": {
        "sendTech": 0,
        "sendCash": 0,
        "getTech": 0,
        "getCash": 0,
        "send_priority": 2,
        "receive_priority": 2
      },
      "current_stats": {
        "technology": "6,391.82",
        "infrastructure": "10,835.30",
        "strength": "82961.755"
      },
      "notes": ""
    },
    "238472": {
      "ruler_name": "Xerxes",
      "nation_name": "New Persia",
      "discord_handle": "",
      "has_dra": false,
      "notes": "",
      "slots": {
        "sendTech": 0,
        "sendCash": 0,
        "getTech": 0,
        "getCash": 0,
        "send_priority": 2,
        "receive_priority": 2
      },
      "current_stats": {
        "technology": "402.62",
        "infrastructure": "12,559.62",
        "strength": "61038.69"
      }
    },
    "243186": {
      "ruler_name": "ditchboy00",
      "nation_name": "Ditchopia",
      "discord_handle": "",
      "has_dra": false,
      "notes": "",
      "slots": {
        "sendTech": 0,
        "sendCash": 0,
        "getTech": 0,
        "getCash": 0,
        "send_priority": 2,
        "receive_priority": 2
      },
      "current_stats": {
        "technology": "6,669.37",
        "infrastructure": "14,999.18",
        "strength": "93456.225"
      }
    },
    "254775": {
      "ruler_name": "Bionic redhead",
      "nation_name": "Bionicus",
      "discord_handle": "",
      "has_dra": true,
      "slots": {
        "sendTech": 0,
        "sendCash": 0,
        "getTech": 0,
        "getCash": 0,
        "send_priority": 2,
        "receive_priority": 2
      },
      "current_stats": {
        "technology": "9,569.75",
        "infrastructure": "13,841.46",
        "strength": "110939.246"
      },
      "notes": ""
    },
    "260817": {
      "ruler_name": "MamazlilMistake",
      "nation_name": "Happy Hunting Ground",
      "discord_handle": "",
      "has_dra": false,
      "notes": "",
      "slots": {
        "sendTech": 0,
        "sendCash": 0,
        "getTech": 0,
        "getCash": 0,
        "send_priority": 3,
        "receive_priority": 3
      },
      "current_stats": {
        "technology": "23,662.43",
        "infrastructure": "3,499.74",
        "strength": "142533.664"
      }
    },
    "264911": {
      "ruler_name": "tgilleland",
      "nation_name": "Murdergascar",
      "discord_handle": "",
      "has_dra": false,
      "notes": "",
      "slots": {
        "sendTech": 0,
        "sendCash": 0,
        "getTech": 0,
        "getCash": 0,
        "send_priority": 3,
        "receive_priority": 3
      },
      "current_stats": {
        "technology": "6,843.00",
        "infrastructure": "17,702.25",
        "strength": "128014.111"
      }
    },
    "273692": {
      "ruler_name": "Pope Bubba XIII",
      "nation_name": "Rebel Virginia",
      "discord_handle": "",
      "has_dra": false,
      "notes": "",
      "slots": {
        "sendTech": 0,
        "sendCash": 0,
        "getTech": 0,
        "getCash": 0,
        "send_priority": 2,
        "receive_priority": 2
      },
      "current_stats": {
        "technology": "8,826.82",
        "infrastructure": "10,606.03",
        "strength": "95495.874"
      }
    },
    "276365": {
      "ruler_name": "ShadowSKAR",
      "nation_name": "Hidden Shadows",
      "discord_handle": "",
      "has_dra": false,
      "notes": "",
      "slots": {
        "sendTech": 0,
        "sendCash": 0,
        "getTech": 0,
        "getCash": 0,
        "send_priority": 2,
        "receive_priority": 2
      },
      "current_stats": {
        "technology": "9,285.27",
        "infrastructure": "5,999.26",
        "strength": "74706.613"
      }
    },
    "288430": {
      "ruler_name": "jrsyboy",
      "nation_name": "toqueville",
      "discord_handle": "",
      "has_dra": false,
      "notes": "",
      "slots": {
        "sendTech": 0,
        "sendCash": 0,
        "getTech": 0,
        "getCash": 0,
        "send_priority": 2,
        "receive_priority": 2
      },
      "current_stats": {
        "technology": "9,342.40",
        "infrastructure": "16,999.99",
        "strength": "122791.052"
      }
    },
    "307315": {
      "ruler_name": "ni431",
      "nation_name": "ni nation",
      "discord_handle": "",
      "has_dra": false,
      "notes": "",
      "slots": {
        "sendTech": 0,
        "sendCash": 0,
        "getTech": 0,
        "getCash": 0,
        "send_priority": 3,
        "receive_priority": 3
      },
      "current_stats": {
        "technology": "9,032.06",
        "infrastructure": "2,028.25",
        "strength": "59299.253"
      }
    },
    "314185": {
      "ruler_name": "Rhizoctonia",
      "nation_name": "Rhizoctonia",
      "discord_handle": "",
      "has_dra": true,
      "slots": {
        "sendTech": 0,
        "sendCash": 0,
        "getTech": 0,
        "getCash": 0,
        "send_priority": 2,
        "receive_priority": 2
      },
      "current_stats": {
        "technology": "6,839.48",
        "infrastructure": "10,162.88",
        "strength": "84491.355"
      },
      "notes": ""
    },
    "319843": {
      "ruler_name": "Sinister",
      "nation_name": "New Terminal",
      "discord_handle": "",
      "has_dra": false,
      "notes": "",
      "slots": {
        "sendTech": 0,
        "sendCash": 0,
        "getTech": 0,
        "getCash": 0,
        "send_priority": 2,
        "receive_priority": 2
      },
      "current_stats": {
        "technology": "8,253.68",
        "infrastructure": "9,999.83",
        "strength": "91327.079"
      }
    },
    "324224": {
      "ruler_name": "SemperFidelis",
      "nation_name": "United Carborundum",
      "discord_handle": "",
      "has_dra": false,
      "notes": "",
      "slots": {
        "sendTech": 0,
        "sendCash": 0,
        "getTech": 0,
        "getCash": 0,
        "send_priority": 2,
        "receive_priority": 2
      },
      "current_stats": {
        "technology": "10,300.67",
        "infrastructure": "9,999.99",
        "strength": "98443.555"
      }
    },
    "327088": {
      "ruler_name": "spearo",
      "nation_name": "Deep Blue",
      "discord_handle": "",
      "has_dra": false,
      "notes": "",
      "slots": {
        "sendTech": 0,
        "sendCash": 0,
        "getTech": 0,
        "getCash": 0,
        "send_priority": 2,
        "receive_priority": 2
      },
      "current_stats": {
        "technology": "8,289.01",
        "infrastructure": "11,561.38",
        "strength": "95709.401"
      }
    },
    "341362": {
      "ruler_name": "Erwin Schrodinger",
      "nation_name": "Bermuda Islands",
      "discord_handle": "",
      "has_dra": true,
      "slots": {
        "sendTech": 0,
        "sendCash": 0,
        "getTech": 0,
        "getCash": 0,
        "send_priority": 2,
        "receive_priority": 2
      },
      "current_stats": {
        "technology": "122.51",
        "infrastructure": "10,971.38",
        "strength": "39131.391"
      },
      "notes": ""
    },
    "369917": {
      "ruler_name": "Gibsonator21",
      "nation_name": "Gibsonistan",
      "discord_handle": "",
      "has_dra": true,
      "slots": {
        "sendTech": 0,
        "sendCash": 0,
        "getTech": 0,
        "getCash": 0,
        "send_priority": 2,
        "receive_priority": 2
      },
      "current_stats": {
        "technology": "385.05",
        "infrastructure": "6,633.25",
        "strength": "27242.018"
      },
      "notes": ""
    },
    "407657": {
      "ruler_name": "Shtanto",
      "nation_name": "Shtanto",
      "discord_handle": "",
      "has_dra": false,
      "notes": "",
      "slots": {
        "sendTech": 0,
        "sendCash": 0,
        "getTech": 0,
        "getCash": 0,
        "send_priority": 2,
        "receive_priority": 2
      },
      "current_stats": {
        "technology": "9,400.90",
        "infrastructure": "9,999.99",
        "strength": "88973.531"
      }
    },
    "418916": {
      "ruler_name": "HeroofTime55",
      "nation_name": "New XGA",
      "discord_handle": "",
      "has_dra": true,
      "slots": {
        "sendTech": 0,
        "sendCash": 0,
        "getTech": 0,
        "getCash": 0,
        "send_priority": 2,
        "receive_priority": 2
      },
      "current_stats": {
        "technology": "7,560.54",
        "infrastructure": "7,863.04",
        "strength": "75758.608"
      },
      "notes": ""
    },
    "437823": {
      "ruler_name": "zyberzpyder",
      "nation_name": "Zyberia",
      "discord_handle": "",
      "has_dra": false,
      "notes": "",
      "slots": {
        "sendTech": 0,
        "sendCash": 0,
        "getTech": 0,
        "getCash": 0,
        "send_priority": 2,
        "receive_priority": 2
      },
      "current_stats": {
        "technology": "8,700.60",
        "infrastructure": "9,999.99",
        "strength": "89726.415"
      }
    },
    "457345": {
      "ruler_name": "Taiki11",
      "nation_name": "Taiki Land",
      "discord_handle": "",
      "has_dra": true,
      "slots": {
        "sendTech": 0,
        "sendCash": 0,
        "getTech": 0,
        "getCash": 0,
        "send_priority": 2,
        "receive_priority": 2
      },
      "current_stats": {
        "technology": "102.76",
        "infrastructure": "3,180.73",
        "strength": "18087.863"
      },
      "notes": ""
    },
    "469301": {
      "ruler_name": "Lars Jorgens",
      "nation_name": "Whale of a Time",
      "discord_handle": "",
      "has_dra": false,
      "notes": "",
      "slots": {
        "sendTech": 0,
        "sendCash": 0,
        "getTech": 0,
        "getCash": 0,
        "send_priority": 2,
        "receive_priority": 2
      },
      "current_stats": {
        "technology": "8,985.49",
        "infrastructure": "8,026.75",
        "strength": "76105.712"
      }
    },
    "473088": {
      "ruler_name": "JuiceBox",
      "nation_name": "Phoenix Isle",
      "discord_handle": "",
      "has_dra": true,
      "slots": {
        "sendTech": 0,
        "sendCash": 0,
        "getTech": 0,
        "getCash": 0,
        "send_priority": 2,
        "receive_priority": 2
      },
      "current_stats": {
        "technology": "9,120.30",
        "infrastructure": "6,870.42",
        "strength": "78917.152"
      },
      "notes": ""
    },
    "474935": {
      "ruler_name": "Enabran Tain",
      "nation_name": "Obsidian Order",
      "discord_handle": "",
      "has_dra": false,
      "notes": "",
      "slots": {
        "sendTech": 0,
        "sendCash": 0,
        "getTech": 0,
        "getCash": 0,
        "send_priority": 2,
        "receive_priority": 2
      },
      "current_stats": {
        "technology": "8,256.12",
        "infrastructure": "11,282.96",
        "strength": "90623.592"
      }
    },
    "475014": {
      "ruler_name": "cirk2",
      "nation_name": "Agatea",
      "discord_handle": "",
      "has_dra": false,
      "notes": "",
      "slots": {
        "sendTech": 0,
        "sendCash": 0,
        "getTech": 0,
        "getCash": 0,
        "send_priority": 3,
        "receive_priority": 3
      },
      "current_stats": {
        "technology": "8,261.56",
        "infrastructure": "4,916.33",
        "strength": "71906.756"
      }
    },
    "484657": {
      "ruler_name": "Augustus Caesar",
      "nation_name": "South Holland",
      "discord_handle": "",
      "has_dra": false,
      "notes": "",
      "slots": {
        "sendTech": 0,
        "sendCash": 0,
        "getTech": 0,
        "getCash": 0,
        "send_priority": 3,
        "receive_priority": 3
      },
      "current_stats": {
        "technology": "3,333.89",
        "infrastructure": "15,998.21",
        "strength": "78572.224"
      }
    },
    "490921": {
      "ruler_name": "Roo Blu II",
      "nation_name": "Blue Roo",
      "discord_handle": "",
      "has_dra": false,
      "notes": "",
      "slots": {
        "sendTech": 0,
        "sendCash": 0,
        "getTech": 0,
        "getCash": 0,
        "send_priority": 2,
        "receive_priority": 2
      },
      "current_stats": {
        "technology": "10,661.98",
        "infrastructure": "8,999.99",
        "strength": "96674.867"
      }
    },
    "500125": {
      "ruler_name": "Soxirella",
      "nation_name": "Jusmania",
      "discord_handle": "",
      "has_dra": false,
      "notes": "",
      "slots": {
        "sendTech": 0,
        "sendCash": 0,
        "getTech": 0,
        "getCash": 0,
        "send_priority": 2,
        "receive_priority": 2
      },
      "current_stats": {
        "technology": "7,608.37",
        "infrastructure": "18,638.63",
        "strength": "117280.752"
      }
    },
    "528479": {
      "ruler_name": "paul711",
      "nation_name": "Paulinca",
      "discord_handle": "",
      "has_dra": false,
      "notes": "",
      "slots": {
        "sendTech": 0,
        "sendCash": 0,
        "getTech": 0,
        "getCash": 0,
        "send_priority": 3,
        "receive_priority": 3
      },
      "current_stats": {
        "technology": "9,595.85",
        "infrastructure": "12,010.54",
        "strength": "98028.163"
      }
    },
    "529964": {
      "ruler_name": "Pelzig",
      "nation_name": "Salusa Secundus",
      "discord_handle": "",
      "has_dra": true,
      "notes": "",
      "slots": {
        "sendTech": 0,
        "sendCash": 0,
        "getTech": 0,
        "getCash": 0,
        "send_priority": 2,
        "receive_priority": 1
      },
      "current_stats": {
        "technology": "723.14",
        "infrastructure": "4,999.99",
        "strength": "26161.393"
      }
    },
    "538259": {
      "ruler_name": "The Big Bad",
      "nation_name": "Empire of the North",
      "discord_handle": "",
      "has_dra": false,
      "notes": "",
      "slots": {
        "sendTech": 0,
        "sendCash": 0,
        "getTech": 0,
        "getCash": 0,
        "send_priority": 3,
        "receive_priority": 3
      },
      "current_stats": {
        "technology": "211.71",
        "infrastructure": "1,555.93",
        "strength": "8066.971"
      }
    },
    "538690": {
      "ruler_name": "CrinkledStraw",
      "nation_name": "The Fierce Crown",
      "discord_handle": "",
      "has_dra": true,
      "slots": {
        "sendTech": 0,
        "sendCash": 0,
        "getTech": 0,
        "getCash": 0,
        "send_priority": 2,
        "receive_priority": 2
      },
      "current_stats": {
        "technology": "111.50",
        "infrastructure": "6,349.72",
        "strength": "24891.61"
      },
      "notes": ""
    },
    "547395": {
      "ruler_name": "KameraadLenin",
      "nation_name": "Newfoundland SSR",
      "discord_handle": "",
      "has_dra": true,
      "slots": {
        "sendTech": 0,
        "sendCash": 0,
        "getTech": 0,
        "getCash": 0,
        "send_priority": 2,
        "receive_priority": 2
      },
      "current_stats": {
        "technology": "503.13",
        "infrastructure": "9,017.03",
        "strength": "38282.071"
      },
      "notes": ""
    },
    "560469": {
      "ruler_name": "draggie",
      "nation_name": "Aporia",
      "discord_handle": "",
      "has_dra": true,
      "notes": "",
      "slots": {
        "sendTech": 0,
        "sendCash": 0,
        "getTech": 0,
        "getCash": 0,
        "send_priority": 2,
        "receive_priority": 2
      },
      "current_stats": {
        "technology": "347.28",
        "infrastructure": "5,961.25",
        "strength": "24577.783"
      }
    },
    "571873": {
      "ruler_name": "Kal Asharak",
      "nation_name": "Ceska Republik",
      "discord_handle": "",
      "has_dra": true,
      "slots": {
        "sendTech": 0,
        "sendCash": 0,
        "getTech": 0,
        "getCash": 0,
        "send_priority": 2,
        "receive_priority": 2
      },
      "current_stats": {
        "technology": "731.59",
        "infrastructure": "11,332.67",
        "strength": "50836.28"
      },
      "notes": ""
    },
    "582941": {
      "ruler_name": "Cydonian Knight",
      "nation_name": "Strodemia",
      "discord_handle": "",
      "has_dra": false,
      "notes": "",
      "slots": {
        "sendTech": 0,
        "sendCash": 0,
        "getTech": 0,
        "getCash": 0,
        "send_priority": 3,
        "receive_priority": 3
      },
      "current_stats": {
        "technology": "11,147.34",
        "infrastructure": "4,040.64",
        "strength": "75020.299"
      }
    },
    "584157": {
      "ruler_name": "Sheekyz",
      "nation_name": "Kingdom Of Xe",
      "discord_handle": "",
      "has_dra": true,
      "slots": {
        "sendTech": 0,
        "sendCash": 0,
        "getTech": 0,
        "getCash": 0,
        "send_priority": 2,
        "receive_priority": 2
      },
      "current_stats": {
        "technology": "5,017.85",
        "infrastructure": "18,730.08",
        "strength": "127359.406"
      },
      "notes": ""
    },
    "588320": {
      "ruler_name": "RUB10",
      "nation_name": "Establishmentaria",
      "discord_handle": "",
      "has_dra": true,
      "slots": {
        "sendTech": 0,
        "sendCash": 0,
        "getTech": 0,
        "getCash": 0,
        "send_priority": 2,
        "receive_priority": 2
      },
      "current_stats": {
        "technology": "365.67",
        "infrastructure": "7,038.59",
        "strength": "37321.891"
      },
      "notes": ""
    },
    "596901": {
      "ruler_name": "Malic",
      "nation_name": "Veridia",
      "discord_handle": "",
      "has_dra": false,
      "notes": "",
      "slots": {
        "sendTech": 0,
        "sendCash": 0,
        "getTech": 0,
        "getCash": 0,
        "send_priority": 2,
        "receive_priority": 2
      },
      "current_stats": {
        "technology": "8,704.93",
        "infrastructure": "7,294.39",
        "strength": "80525.245"
      }
    },
    "599455": {
      "ruler_name": "RearviewRover",
      "nation_name": "Prossy Boat Party",
      "discord_handle": "",
      "has_dra": false,
      "notes": "",
      "slots": {
        "sendTech": 0,
        "sendCash": 0,
        "getTech": 0,
        "getCash": 0,
        "send_priority": 3,
        "receive_priority": 3
      },
      "current_stats": {
        "technology": "100.37",
        "infrastructure": "12,999.99",
        "strength": "49544.324"
      }
    },
    "600902": {
      "ruler_name": "HackSlash",
      "nation_name": "NewFinlandia",
      "discord_handle": "",
      "has_dra": false,
      "notes": "",
      "slots": {
        "sendTech": 0,
        "sendCash": 0,
        "getTech": 0,
        "getCash": 0,
        "send_priority": 2,
        "receive_priority": 2
      },
      "current_stats": {
        "technology": "8,934.37",
        "infrastructure": "8,218.67",
        "strength": "88399.796"
      }
    },
    "612276": {
      "ruler_name": "Ascended Dio",
      "nation_name": "The Nootropics",
      "discord_handle": "",
      "has_dra": false,
      "notes": "",
      "slots": {
        "sendTech": 0,
        "sendCash": 0,
        "getTech": 0,
        "getCash": 0,
        "send_priority": 3,
        "receive_priority": 3
      },
      "current_stats": {
        "technology": "159.13",
        "infrastructure": "2,999.99",
        "strength": "12186.092"
      }
    },
    "613432": {
      "ruler_name": "Talbrys",
      "nation_name": "Keltroy",
      "discord_handle": "",
      "has_dra": false,
      "notes": "",
      "slots": {
        "sendTech": 0,
        "sendCash": 0,
        "getTech": 0,
        "getCash": 0,
        "send_priority": 2,
        "receive_priority": 2
      },
      "current_stats": {
        "technology": "7,475.30",
        "infrastructure": "11,880.40",
        "strength": "99219.641"
      }
    },
    "618150": {
      "ruler_name": "Lyanna Mormont",
      "nation_name": "Bear Island 4 Lyfe",
      "discord_handle": "",
      "has_dra": false,
      "notes": "",
      "slots": {
        "sendTech": 0,
        "sendCash": 0,
        "getTech": 0,
        "getCash": 0,
        "send_priority": 3,
        "receive_priority": 3
      },
      "current_stats": {
        "technology": "1,076.10",
        "infrastructure": "12,491.05",
        "strength": "63464.075"
      }
    },
    "623644": {
      "ruler_name": "Van Hoo X",
      "nation_name": "Hoovokia",
      "discord_handle": "",
      "has_dra": true,
      "slots": {
        "sendTech": 0,
        "sendCash": 0,
        "getTech": 0,
        "getCash": 0,
        "send_priority": 2,
        "receive_priority": 2
      },
      "current_stats": {
        "technology": "454.78",
        "infrastructure": "3,123.31",
        "strength": "16264.929"
      },
      "notes": ""
    },
    "624193": {
      "ruler_name": "The1nonlykk",
      "nation_name": "Biourja",
      "discord_handle": "",
      "has_dra": true,
      "notes": "",
      "slots": {
        "sendTech": 0,
        "sendCash": 0,
        "getTech": 0,
        "getCash": 0,
        "send_priority": 2,
        "receive_priority": 1
      },
      "current_stats": {
        "technology": "75.68",
        "infrastructure": "7,250.03",
        "strength": "25230.263"
      }
    },
    "625902": {
      "ruler_name": "Patrick Stewart",
      "nation_name": "Republic of Yorkshir",
      "discord_handle": "",
      "has_dra": false,
      "notes": "",
      "slots": {
        "sendTech": 0,
        "sendCash": 0,
        "getTech": 0,
        "getCash": 0,
        "send_priority": 2,
        "receive_priority": 2
      },
      "current_stats": {
        "technology": "133.89",
        "infrastructure": "3,047.85",
        "strength": "16860.189"
      }
    },
    "626678": {
      "ruler_name": "slothix",
      "nation_name": "Kevin",
      "discord_handle": "",
      "has_dra": true,
      "slots": {
        "sendTech": 0,
        "sendCash": 0,
        "getTech": 0,
        "getCash": 0,
        "send_priority": 2,
        "receive_priority": 2
      },
      "current_stats": {
        "technology": "307.53",
        "infrastructure": "5,914.12",
        "strength": "30050.077"
      },
      "notes": ""
    },
    "626737": {
      "ruler_name": "BigFilthyDick",
      "nation_name": "GayBar",
      "discord_handle": "",
      "has_dra": true,
      "slots": {
        "sendTech": 0,
        "sendCash": 0,
        "getTech": 0,
        "getCash": 0,
        "send_priority": 2,
        "receive_priority": 2
      },
      "current_stats": {
        "technology": "105.21",
        "infrastructure": "14,699.03",
        "strength": "60059.794"
      },
      "notes": ""
    },
    "626980": {
      "ruler_name": "Aspire",
      "nation_name": "AspireFerty",
      "discord_handle": "",
      "has_dra": false,
      "notes": "",
      "slots": {
        "sendTech": 0,
        "sendCash": 0,
        "getTech": 0,
        "getCash": 0,
        "send_priority": 3,
        "receive_priority": 3
      },
      "current_stats": {
        "technology": "7,512.83",
        "infrastructure": "5,036.03",
        "strength": "62352.046"
      }
    },
    "627572": {
      "ruler_name": "Latexi",
      "nation_name": "Why would I do this",
      "discord_handle": "",
      "has_dra": false,
      "notes": "",
      "slots": {
        "sendTech": 0,
        "sendCash": 0,
        "getTech": 0,
        "getCash": 0,
        "send_priority": 2,
        "receive_priority": 2
      },
      "current_stats": {
        "technology": "500.15",
        "infrastructure": "9,936.49",
        "strength": "54867.928"
      }
    },
    "630971": {
      "ruler_name": "Jeremiah",
      "nation_name": "CERAVA",
      "discord_handle": "",
      "has_dra": true,
      "slots": {
        "sendTech": 0,
        "sendCash": 0,
        "getTech": 0,
        "getCash": 0,
        "send_priority": 2,
        "receive_priority": 2
      },
      "current_stats": {
        "technology": "778.85",
        "infrastructure": "13,429.90",
        "strength": "60973.919"
      },
      "notes": ""
    },
    "631302": {
      "ruler_name": "Gatherum",
      "nation_name": "Vermis",
      "discord_handle": "",
      "has_dra": true,
      "slots": {
        "sendTech": 0,
        "sendCash": 0,
        "getTech": 0,
        "getCash": 0,
        "send_priority": 2,
        "receive_priority": 2
      },
      "current_stats": {
        "technology": "510.75",
        "infrastructure": "10,499.99",
        "strength": "47090.79"
      },
      "notes": ""
    },
    "631569": {
      "ruler_name": "CaesarGorandius",
      "nation_name": "Ohiostan",
      "discord_handle": "",
      "has_dra": true,
      "slots": {
        "sendTech": 0,
        "sendCash": 0,
        "getTech": 0,
        "getCash": 0,
        "send_priority": 2,
        "receive_priority": 2
      },
      "current_stats": {
        "technology": "200.06",
        "infrastructure": "7,211.41",
        "strength": "33246.868"
      },
      "notes": ""
    },
    "633611": {
      "ruler_name": "Speeder",
      "nation_name": "Dronterlands",
      "discord_handle": "",
      "has_dra": false,
      "notes": "",
      "slots": {
        "sendTech": 0,
        "sendCash": 0,
        "getTech": 0,
        "getCash": 0
      },
      "current_stats": {
        "technology": "145.77",
        "infrastructure": "10,048.11",
        "strength": "40273.048"
      }
    },
    "634448": {
      "ruler_name": "Stewie",
      "nation_name": "Stewieland III",
      "discord_handle": "",
      "has_dra": true,
      "slots": {
        "sendTech": 0,
        "sendCash": 0,
        "getTech": 0,
        "getCash": 0,
        "send_priority": 2,
        "receive_priority": 2
      },
      "current_stats": {
        "technology": "7,669.84",
        "infrastructure": "10,654.65",
        "strength": "95073.249"
      },
      "notes": ""
    },
    "634597": {
      "ruler_name": "LiaColle",
      "nation_name": "Prynthian",
      "discord_handle": "",
      "has_dra": true,
      "slots": {
        "sendTech": 0,
        "sendCash": 0,
        "getTech": 0,
        "getCash": 0,
        "send_priority": 2,
        "receive_priority": 2
      },
      "current_stats": {
        "technology": "190.92",
        "infrastructure": "3,721.85",
        "strength": "14069.613"
      },
      "notes": ""
    },
    "634903": {
      "ruler_name": "ToasterOven",
      "nation_name": "Pancake Republic",
      "discord_handle": "",
      "has_dra": false,
      "notes": "",
      "slots": {
        "sendTech": 0,
        "sendCash": 0,
        "getTech": 0,
        "getCash": 0,
        "send_priority": 3,
        "receive_priority": 3
      },
      "current_stats": {
        "technology": "100.90",
        "infrastructure": "10,999.99",
        "strength": "44772.758"
      }
    },
    "638461": {
      "ruler_name": "Jerby",
      "nation_name": "Simulacra",
      "discord_handle": "",
      "has_dra": false,
      "notes": "",
      "slots": {
        "sendTech": 0,
        "sendCash": 0,
        "getTech": 0,
        "getCash": 0
      },
      "current_stats": {
        "technology": "353.37",
        "infrastructure": "10,260.25",
        "strength": "42392.478"
      }
    },
    "638567": {
      "ruler_name": "Cobert",
      "nation_name": "Brightwood",
      "discord_handle": "",
      "has_dra": true,
      "slots": {
        "sendTech": 0,
        "sendCash": 0,
        "getTech": 0,
        "getCash": 0,
        "send_priority": 2,
        "receive_priority": 2
      },
      "current_stats": {
        "technology": "122.53",
        "infrastructure": "5,038.52",
        "strength": "23503.457"
      },
      "notes": ""
    },
    "638747": {
      "ruler_name": "Medic IV",
      "nation_name": "Deutschland II",
      "discord_handle": "",
      "has_dra": false,
      "notes": "",
      "slots": {
        "sendTech": 0,
        "sendCash": 0,
        "getTech": 0,
        "getCash": 0,
        "send_priority": 3,
        "receive_priority": 3
      },
      "current_stats": {
        "technology": "110.44",
        "infrastructure": "1,399.97",
        "strength": "5918.148"
      }
    },
    "639721": {
      "ruler_name": "TheCompany0",
      "nation_name": "Malacipe",
      "discord_handle": "",
      "has_dra": false,
      "notes": "",
      "slots": {
        "sendTech": 0,
        "sendCash": 0,
        "getTech": 0,
        "getCash": 0,
        "send_priority": 3,
        "receive_priority": 3
      },
      "current_stats": {
        "technology": "602.10",
        "infrastructure": "8,588.18",
        "strength": "43076.121"
      }
    },
    "643981": {
      "ruler_name": "ONXwat",
      "nation_name": "Vanier",
      "discord_handle": "",
      "has_dra": false,
      "notes": "",
      "slots": {
        "sendTech": 0,
        "sendCash": 0,
        "getTech": 0,
        "getCash": 0,
        "send_priority": 3,
        "receive_priority": 3
      },
      "current_stats": {
        "technology": "291.43",
        "infrastructure": "3,895.11",
        "strength": "16749.685"
      }
    },
    "644042": {
      "ruler_name": "calicocatface",
      "nation_name": "Calico Islands",
      "discord_handle": "",
      "has_dra": true,
      "slots": {
        "sendTech": 0,
        "sendCash": 0,
        "getTech": 0,
        "getCash": 0,
        "send_priority": 2,
        "receive_priority": 2
      },
      "current_stats": {
        "technology": "554.57",
        "infrastructure": "5,999.99",
        "strength": "28289.127"
      },
      "notes": ""
    },
    "645844": {
      "ruler_name": "Dario the Great",
      "nation_name": "Darioland",
      "discord_handle": "",
      "has_dra": false,
      "notes": "",
      "slots": {
        "sendTech": 0,
        "sendCash": 0,
        "getTech": 0,
        "getCash": 0,
        "send_priority": 3,
        "receive_priority": 3
      },
      "current_stats": {
        "technology": "85.23",
        "infrastructure": "1,000.01",
        "strength": "4365.287"
      }
    },
    "645946": {
      "ruler_name": "LiFeng",
      "nation_name": "Qwertyiop",
      "discord_handle": "",
      "has_dra": true,
      "notes": "",
      "slots": {
        "sendTech": 0,
        "sendCash": 0,
        "getTech": 0,
        "getCash": 0,
        "send_priority": 2,
        "receive_priority": 2
      },
      "current_stats": {
        "technology": "59.60",
        "infrastructure": "6,695.64",
        "strength": "26795.08"
      }
    },
    "646167": {
      "ruler_name": "DoctorDlicious",
      "nation_name": "Lat Flan",
      "discord_handle": "",
      "has_dra": false,
      "notes": "",
      "slots": {
        "sendTech": 0,
        "sendCash": 0,
        "getTech": 0,
        "getCash": 0,
        "send_priority": 3,
        "receive_priority": 3
      },
      "current_stats": {
        "technology": "169.93",
        "infrastructure": "2,838.32",
        "strength": "12017.922"
      }
    },
    "646950": {
      "ruler_name": "KarmaBlaster",
      "nation_name": "NoNameIstan",
      "discord_handle": "",
      "has_dra": false,
      "notes": "",
      "slots": {
        "sendTech": 0,
        "sendCash": 0,
        "getTech": 0,
        "getCash": 0,
        "send_priority": 3,
        "receive_priority": 3
      },
      "current_stats": {
        "technology": "100.00",
        "infrastructure": "600.00",
        "strength": "2969.54"
      }
    },
    "646989": {
      "ruler_name": "LordSciolist",
      "nation_name": "Chaleroux",
      "discord_handle": "",
      "has_dra": false,
      "notes": "",
      "slots": {
        "sendTech": 0,
        "sendCash": 0,
        "getTech": 0,
        "getCash": 0,
        "send_priority": 2,
        "receive_priority": 1
      },
      "current_stats": {
        "technology": "3.66",
        "infrastructure": "501.00",
        "strength": "1630.725"
      }
    },
    "647005": {
      "ruler_name": "oalf222444",
      "nation_name": "Ragnorakia",
      "discord_handle": "",
      "has_dra": false,
      "notes": "",
      "slots": {
        "sendTech": 0,
        "sendCash": 0,
        "getTech": 0,
        "getCash": 0,
        "send_priority": 3,
        "receive_priority": 3
      },
      "current_stats": {
        "technology": "37.50",
        "infrastructure": "520.86",
        "strength": "2236.478"
      }
    },
    "647200": {
      "ruler_name": "InsiderThreat",
      "nation_name": "The Silent Proxy",
      "discord_handle": "",
      "has_dra": true,
      "notes": "",
      "slots": {
        "sendTech": 0,
        "sendCash": 0,
        "getTech": 0,
        "getCash": 0,
        "send_priority": 2,
        "receive_priority": 2
      },
      "current_stats": {
        "technology": "500.31",
        "infrastructure": "6,581.87",
        "strength": "26830.709"
      }
    }
  }
}