{
  "alliance_id": 17368,
  "alliance_name": "Doombrella",
  "nations": {
    "33521": {
      "ruler_name": "Crymson",
      "nation_name": "Crymson",
      "discord_handle": "",
      "has_dra": false,
      "notes": "",
      "slots": {
        "sendTech": 0,
        "sendCash": 0,
        "getTech": 0,
        "getCash": 0,
        "send_priority": 3,
        "receive_priority": 3
      },
      "current_stats": {
        "technology": "597.38",
        "infrastructure": "9,402.65",
        "strength": "36838.559"
      }
    },
    "66883": {
      "ruler_name": "Crown Prince Mishka",
      "nation_name": "Tygaland",
      "discord_handle": "",
      "has_dra": false,
      "notes": "",
      "slots": {
        "sendTech": 0,
        "sendCash": 0,
        "getTech": 0,
        "getCash": 0,
        "send_priority": 3,
        "receive_priority": 3
      },
      "current_stats": {
        "technology": "20,571.08",
        "infrastructure": "12,355.23",
        "strength": "157916.577"
      }
    },
    "101493": {
      "ruler_name": "ak47don",
      "nation_name": "sicily mafia",
      "discord_handle": "",
      "has_dra": false,
      "notes": "",
      "slots": {
        "sendTech": 0,
        "sendCash": 0,
        "getTech": 0,
        "getCash": 0,
        "send_priority": 3,
        "receive_priority": 3
      },
      "current_stats": {
        "technology": "18,539.92",
        "infrastructure": "729.31",
        "strength": "94887.513"
      }
    },
    "127226": {
      "ruler_name": "LJ Scott",
      "nation_name": "Republic of Jutland",
      "discord_handle": "",
      "has_dra": false,
      "notes": "",
      "slots": {
        "sendTech": 0,
        "sendCash": 0,
        "getTech": 0,
        "getCash": 0,
        "send_priority": 3,
        "receive_priority": 3
      },
      "current_stats": {
        "technology": "48,442.16",
        "infrastructure": "8,479.78",
        "strength": "285797.323"
      }
    },
    "139809": {
      "ruler_name": "John Orris",
      "nation_name": "Commonwealth of John",
      "discord_handle": "",
      "has_dra": false,
      "notes": "",
      "slots": {
        "sendTech": 0,
        "sendCash": 0,
        "getTech": 0,
        "getCash": 0,
        "send_priority": 3,
        "receive_priority": 3
      },
      "current_stats": {
        "technology": "19,853.41",
        "infrastructure": "9,327.46",
        "strength": "142538.607"
      }
    },
    "141164": {
      "ruler_name": "LiquidMercury",
      "nation_name": "FallenSeraphim",
      "discord_handle": "",
      "has_dra": true,
      "notes": "",
      "slots": {
        "sendTech": 0,
        "sendCash": 3,
        "getTech": 3,
        "getCash": 0,
        "send_priority": 3,
        "receive_priority": 2
      },
      "current_stats": {
        "technology": "71,906.87",
        "infrastructure": "8,149.89",
        "strength": "407187.121"
      }
    },
    "142120": {
      "ruler_name": "Commander Thrawn",
      "nation_name": "Csilla",
      "discord_handle": "",
      "has_dra": false,
      "notes": "",
      "slots": {
        "sendTech": 0,
        "sendCash": 0,
        "getTech": 0,
        "getCash": 0,
        "send_priority": 3,
        "receive_priority": 3
      },
      "current_stats": {
        "technology": "30,324.08",
        "infrastructure": "799.75",
        "strength": "165003.212"
      }
    },
    "144708": {
      "ruler_name": "Matthew PK",
      "nation_name": "Commonwealth of LoL",
      "discord_handle": "",
      "has_dra": false,
      "notes": "",
      "slots": {
        "sendTech": 0,
        "sendCash": 0,
        "getTech": 0,
        "getCash": 0,
        "send_priority": 3,
        "receive_priority": 3
      },
      "current_stats": {
        "technology": "30,177.03",
        "infrastructure": "6,473.86",
        "strength": "208476.979"
      }
    },
    "148460": {
      "ruler_name": "Buds The Man",
      "nation_name": "New Budsland",
      "discord_handle": "",
      "has_dra": false,
      "notes": "",
      "slots": {
        "sendTech": 0,
        "sendCash": 0,
        "getTech": 0,
        "getCash": 0,
        "send_priority": 3,
        "receive_priority": 3
      },
      "current_stats": {
        "technology": "5,409.03",
        "infrastructure": "3,876.94",
        "strength": "40311.599"
      }
    },
    "151268": {
      "ruler_name": "Zerileous",
      "nation_name": "Monkey Time",
      "discord_handle": "",
      "has_dra": false,
      "notes": "",
      "slots": {
        "sendTech": 0,
        "sendCash": 0,
        "getTech": 0,
        "getCash": 0,
        "send_priority": 3,
        "receive_priority": 3
      },
      "current_stats": {
        "technology": "28,378.08",
        "infrastructure": "3,500.76",
        "strength": "160354.242"
      }
    },
    "184221": {
      "ruler_name": "Lizzzz",
      "nation_name": "Elisabethan",
      "discord_handle": "",
      "has_dra": false,
      "notes": "",
      "slots": {
        "sendTech": 0,
        "sendCash": 0,
        "getTech": 0,
        "getCash": 0,
        "send_priority": 3,
        "receive_priority": 3
      },
      "current_stats": {
        "technology": "6,116.17",
        "infrastructure": "9,756.79",
        "strength": "63619.078"
      }
    },
    "184514": {
      "ruler_name": "Franz Ferdinand",
      "nation_name": "L252beck",
      "discord_handle": "",
      "has_dra": false,
      "notes": "",
      "slots": {
        "sendTech": 0,
        "sendCash": 0,
        "getTech": 0,
        "getCash": 0,
        "send_priority": 3,
        "receive_priority": 3
      },
      "current_stats": {
        "technology": "22,993.64",
        "infrastructure": "4,000.01",
        "strength": "138427.079"
      }
    },
    "187132": {
      "ruler_name": "White Majik",
      "nation_name": "VSOP United",
      "discord_handle": "",
      "has_dra": false,
      "notes": "",
      "slots": {
        "sendTech": 0,
        "sendCash": 0,
        "getTech": 0,
        "getCash": 0,
        "send_priority": 3,
        "receive_priority": 3
      },
      "current_stats": {
        "technology": "31,644.16",
        "infrastructure": "4,770.72",
        "strength": "185900.957"
      }
    },
    "199494": {
      "ruler_name": "Bomber66",
      "nation_name": "Baxter",
      "discord_handle": "",
      "has_dra": false,
      "notes": "",
      "slots": {
        "sendTech": 0,
        "sendCash": 0,
        "getTech": 0,
        "getCash": 0,
        "send_priority": 3,
        "receive_priority": 3
      },
      "current_stats": {
        "technology": "16,846.83",
        "infrastructure": "12,693.81",
        "strength": "141684.569"
      }
    },
    "202255": {
      "ruler_name": "onelove",
      "nation_name": "We Are One Love",
      "discord_handle": "",
      "has_dra": false,
      "notes": "",
      "slots": {
        "sendTech": 0,
        "sendCash": 0,
        "getTech": 0,
        "getCash": 0,
        "send_priority": 3,
        "receive_priority": 3
      },
      "current_stats": {
        "technology": "41,541.73",
        "infrastructure": "2,000.99",
        "strength": "214736.506"
      }
    },
    "230799": {
      "ruler_name": "Raymond Jaeger",
      "nation_name": "New Alabama",
      "discord_handle": "",
      "has_dra": false,
      "notes": "",
      "slots": {
        "sendTech": 0,
        "sendCash": 0,
        "getTech": 0,
        "getCash": 0,
        "send_priority": 3,
        "receive_priority": 3
      },
      "current_stats": {
        "technology": "120,687.43",
        "infrastructure": "32,299.99",
        "strength": "748141.177"
      }
    },
    "334182": {
      "ruler_name": "st6mm",
      "nation_name": "Northern Reich",
      "discord_handle": "",
      "has_dra": true,
      "slots": {
        "sendTech": 0,
        "sendCash": 3,
        "getTech": 3,
        "getCash": 0,
        "send_priority": 1,
        "receive_priority": 3
      },
      "current_stats": {
        "technology": "90,237.73",
        "infrastructure": "11,186.32",
        "strength": "506939.872"
      },
      "notes": ""
    },
    "340559": {
      "ruler_name": "paperwings2007",
      "nation_name": "Paper Island",
      "discord_handle": "",
      "has_dra": false,
      "notes": "",
      "slots": {
        "sendTech": 0,
        "sendCash": 0,
        "getTech": 0,
        "getCash": 0,
        "send_priority": 3,
        "receive_priority": 3
      },
      "current_stats": {
        "technology": "2,914.59",
        "infrastructure": "4,828.89",
        "strength": "42367.516"
      }
    },
    "342957": {
      "ruler_name": "tayloj7",
      "nation_name": "Rabbitopia",
      "discord_handle": "",
      "has_dra": false,
      "notes": "",
      "slots": {
        "sendTech": 0,
        "sendCash": 0,
        "getTech": 0,
        "getCash": 0,
        "send_priority": 3,
        "receive_priority": 3
      },
      "current_stats": {
        "technology": "21,679.61",
        "infrastructure": "5,507.43",
        "strength": "130709.853"
      }
    },
    "356682": {
      "ruler_name": "Logic",
      "nation_name": "8Bit Nation",
      "discord_handle": "",
      "has_dra": false,
      "notes": "",
      "slots": {
        "sendTech": 0,
        "sendCash": 0,
        "getTech": 0,
        "getCash": 0,
        "send_priority": 3,
        "receive_priority": 3
      },
      "current_stats": {
        "technology": "184.15",
        "infrastructure": "1,870.61",
        "strength": "11236.548"
      }
    },
    "374321": {
      "ruler_name": "Clash",
      "nation_name": "Discord",
      "discord_handle": "",
      "has_dra": false,
      "notes": "",
      "slots": {
        "sendTech": 0,
        "sendCash": 0,
        "getTech": 0,
        "getCash": 0,
        "send_priority": 3,
        "receive_priority": 3
      },
      "current_stats": {
        "technology": "39,294.50",
        "infrastructure": "4,287.89",
        "strength": "226776.987"
      }
    },
    "402492": {
      "ruler_name": "NikolaP",
      "nation_name": "Wiggles",
      "discord_handle": "",
      "has_dra": false,
      "notes": "",
      "slots": {
        "sendTech": 0,
        "sendCash": 0,
        "getTech": 0,
        "getCash": 0,
        "send_priority": 3,
        "receive_priority": 3
      },
      "current_stats": {
        "technology": "11,657.40",
        "infrastructure": "889.50",
        "strength": "68937.268"
      }
    },
    "426185": {
      "ruler_name": "DeathAdder",
      "nation_name": "Westfalen",
      "discord_handle": "",
      "has_dra": false,
      "notes": "",
      "slots": {
        "sendTech": 0,
        "sendCash": 0,
        "getTech": 0,
        "getCash": 0,
        "send_priority": 3,
        "receive_priority": 3
      },
      "current_stats": {
        "technology": "400.74",
        "infrastructure": "3,396.67",
        "strength": "17489.563"
      }
    },
    "433854": {
      "ruler_name": "Auctor",
      "nation_name": "Wyrdgar",
      "discord_handle": "",
      "has_dra": false,
      "notes": "",
      "slots": {
        "sendTech": 0,
        "sendCash": 0,
        "getTech": 0,
        "getCash": 0,
        "send_priority": 3,
        "receive_priority": 3
      },
      "current_stats": {
        "technology": "200.40",
        "infrastructure": "2,162.57",
        "strength": "11122.417"
      }
    },
    "445021": {
      "ruler_name": "Mogar",
      "nation_name": "Mogatopia",
      "discord_handle": "",
      "has_dra": false,
      "notes": "",
      "slots": {
        "sendTech": 0,
        "sendCash": 0,
        "getTech": 0,
        "getCash": 0,
        "send_priority": 3,
        "receive_priority": 3
      },
      "current_stats": {
        "technology": "400.78",
        "infrastructure": "5,716.70",
        "strength": "27114.483"
      }
    },
    "446109": {
      "ruler_name": "VVhite Majik",
      "nation_name": "VS0P United",
      "discord_handle": "",
      "has_dra": false,
      "notes": "",
      "slots": {
        "sendTech": 0,
        "sendCash": 0,
        "getTech": 0,
        "getCash": 0,
        "send_priority": 3,
        "receive_priority": 3
      },
      "current_stats": {
        "technology": "210.21",
        "infrastructure": "2,044.80",
        "strength": "14316.684"
      }
    },
    "470323": {
      "ruler_name": "plaw44",
      "nation_name": "infinite desire",
      "discord_handle": "",
      "has_dra": false,
      "notes": "",
      "slots": {
        "sendTech": 0,
        "sendCash": 0,
        "getTech": 0,
        "getCash": 0,
        "send_priority": 3,
        "receive_priority": 3
      },
      "current_stats": {
        "technology": "65,444.74",
        "infrastructure": "11,208.46",
        "strength": "414465.498"
      }
    },
    "481103": {
      "ruler_name": "AzureShadow",
      "nation_name": "Coobie",
      "discord_handle": "",
      "has_dra": false,
      "notes": "",
      "slots": {
        "sendTech": 0,
        "sendCash": 0,
        "getTech": 0,
        "getCash": 0,
        "send_priority": 3,
        "receive_priority": 3
      },
      "current_stats": {
        "technology": "420.11",
        "infrastructure": "2,391.31",
        "strength": "11702.242"
      }
    },
    "484851": {
      "ruler_name": "enderland",
      "nation_name": "Fields of Elysium",
      "discord_handle": "",
      "has_dra": false,
      "notes": "",
      "slots": {
        "sendTech": 0,
        "sendCash": 0,
        "getTech": 0,
        "getCash": 0,
        "send_priority": 3,
        "receive_priority": 3
      },
      "current_stats": {
        "technology": "25,413.59",
        "infrastructure": "8,610.81",
        "strength": "170305.904"
      }
    },
    "502087": {
      "ruler_name": "Astryl",
      "nation_name": "Ethereal",
      "discord_handle": "",
      "has_dra": false,
      "notes": "",
      "slots": {
        "sendTech": 0,
        "sendCash": 0,
        "getTech": 0,
        "getCash": 0,
        "send_priority": 3,
        "receive_priority": 3
      },
      "current_stats": {
        "technology": "27,944.68",
        "infrastructure": "17,999.99",
        "strength": "226748.867"
      }
    },
    "503436": {
      "ruler_name": "StevieG",
      "nation_name": "Dinglebay",
      "discord_handle": "",
      "has_dra": false,
      "notes": "",
      "slots": {
        "sendTech": 0,
        "sendCash": 0,
        "getTech": 0,
        "getCash": 0,
        "send_priority": 3,
        "receive_priority": 3
      },
      "current_stats": {
        "technology": "32,277.65",
        "infrastructure": "4,133.02",
        "strength": "185022.129"
      }
    },
    "541774": {
      "ruler_name": "Das Blitzkrieger",
      "nation_name": "Leistungsstarke",
      "discord_handle": "",
      "has_dra": false,
      "notes": "",
      "slots": {
        "sendTech": 0,
        "sendCash": 0,
        "getTech": 0,
        "getCash": 0,
        "send_priority": 3,
        "receive_priority": 3
      },
      "current_stats": {
        "technology": "58,092.03",
        "infrastructure": "9,809.26",
        "strength": "342029.238"
      }
    },
    "566736": {
      "ruler_name": "amossio",
      "nation_name": "amossio",
      "discord_handle": "",
      "has_dra": false,
      "notes": "",
      "slots": {
        "sendTech": 0,
        "sendCash": 0,
        "getTech": 0,
        "getCash": 0,
        "send_priority": 3,
        "receive_priority": 3
      },
      "current_stats": {
        "technology": "143.27",
        "infrastructure": "1,148.60",
        "strength": "6753.147"
      }
    },
    "567720": {
      "ruler_name": "Cosmic Chocolate",
      "nation_name": "Soaring Eagle",
      "discord_handle": "",
      "has_dra": false,
      "notes": "",
      "slots": {
        "sendTech": 0,
        "sendCash": 0,
        "getTech": 0,
        "getCash": 0,
        "send_priority": 3,
        "receive_priority": 3
      },
      "current_stats": {
        "technology": "10,315.15",
        "infrastructure": "4,106.82",
        "strength": "73081.383"
      }
    },
    "582974": {
      "ruler_name": "SeekerSeeks",
      "nation_name": "Seeking",
      "discord_handle": "",
      "has_dra": false,
      "notes": "",
      "slots": {
        "sendTech": 0,
        "sendCash": 0,
        "getTech": 0,
        "getCash": 0,
        "send_priority": 3,
        "receive_priority": 3
      },
      "current_stats": {
        "technology": "600.00",
        "infrastructure": "8,500.00",
        "strength": "50863.541"
      }
    },
    "585631": {
      "ruler_name": "Srivatsan",
      "nation_name": "MAHANADU",
      "discord_handle": "",
      "has_dra": true,
      "slots": {
        "sendTech": 0,
        "sendCash": 6,
        "getTech": 0,
        "getCash": 0,
        "send_priority": 1,
        "receive_priority": 2
      },
      "current_stats": {
        "technology": "56,299.07",
        "infrastructure": "25,999.99",
        "strength": "402169.026"
      },
      "notes": ""
    },
    "619806": {
      "ruler_name": "Epimethys",
      "nation_name": "Pyrrha",
      "discord_handle": "",
      "has_dra": false,
      "notes": "",
      "slots": {
        "sendTech": 0,
        "sendCash": 0,
        "getTech": 0,
        "getCash": 0,
        "send_priority": 3,
        "receive_priority": 3
      },
      "current_stats": {
        "technology": "100.00",
        "infrastructure": "4,999.99",
        "strength": "15791.885"
      }
    },
    "623822": {
      "ruler_name": "Comrade Marx",
      "nation_name": "GreaterGoonSyndicate",
      "discord_handle": "",
      "has_dra": false,
      "notes": "",
      "slots": {
        "sendTech": 0,
        "sendCash": 0,
        "getTech": 0,
        "getCash": 0,
        "send_priority": 3,
        "receive_priority": 3
      },
      "current_stats": {
        "technology": "17,048.62",
        "infrastructure": "13,613.36",
        "strength": "152639.523"
      }
    },
    "626860": {
      "ruler_name": "BringMeTheHorizon",
      "nation_name": "Dakotas",
      "discord_handle": "",
      "has_dra": false,
      "notes": "",
      "slots": {
        "sendTech": 0,
        "sendCash": 0,
        "getTech": 0,
        "getCash": 0,
        "send_priority": 3,
        "receive_priority": 3
      },
      "current_stats": {
        "technology": "16,442.61",
        "infrastructure": "5,528.71",
        "strength": "109552.855"
      }
    },
    "627592": {
      "ruler_name": "Lord Xamaeron",
      "nation_name": "Celtic Forest",
      "discord_handle": "",
      "has_dra": false,
      "notes": "",
      "slots": {
        "sendTech": 0,
        "sendCash": 0,
        "getTech": 0,
        "getCash": 0,
        "send_priority": 3,
        "receive_priority": 3
      },
      "current_stats": {
        "technology": "12,077.86",
        "infrastructure": "11,111.28",
        "strength": "117314.735"
      }
    },
    "634284": {
      "ruler_name": "mikeymikes",
      "nation_name": "batmanism",
      "discord_handle": "",
      "has_dra": false,
      "notes": "",
      "slots": {
        "sendTech": 0,
        "sendCash": 0,
        "getTech": 0,
        "getCash": 0,
        "send_priority": 3,
        "receive_priority": 3
      },
      "current_stats": {
        "technology": "4,185.59",
        "infrastructure": "4,193.86",
        "strength": "41332.943"
      }
    },
    "635159": {
      "ruler_name": "xAnri",
      "nation_name": "xRoan",
      "discord_handle": "",
      "has_dra": false,
      "notes": "",
      "slots": {
        "sendTech": 0,
        "sendCash": 0,
        "getTech": 0,
        "getCash": 0,
        "send_priority": 3,
        "receive_priority": 3
      },
      "current_stats": {
        "technology": "200.67",
        "infrastructure": "4,999.99",
        "strength": "16883.591"
      }
    },
    "645236": {
      "ruler_name": "Roq Fanclub Presiden",
      "nation_name": "Roq Fanclub",
      "discord_handle": "",
      "has_dra": false,
      "notes": "",
      "slots": {
        "sendTech": 0,
        "sendCash": 0,
        "getTech": 0,
        "getCash": 0,
        "send_priority": 3,
        "receive_priority": 3
      },
      "current_stats": {
        "technology": "100.32",
        "infrastructure": "4,999.99",
        "strength": "19145.196"
      }
    },
    "645427": {
      "ruler_name": "Clank",
      "nation_name": "Clank",
      "discord_handle": "",
      "has_dra": false,
      "notes": "",
      "slots": {
        "sendTech": 0,
        "sendCash": 0,
        "getTech": 0,
        "getCash": 0,
        "send_priority": 3,
        "receive_priority": 3
      },
      "current_stats": {
        "technology": "312.40",
        "infrastructure": "4,965.56",
        "strength": "22322.589"
      }
    },
    "645571": {
      "ruler_name": "cantbelieveimback",
      "nation_name": "Techlandia",
      "discord_handle": "",
      "has_dra": false,
      "notes": "",
      "slots": {
        "sendTech": 0,
        "sendCash": 0,
        "getTech": 0,
        "getCash": 0,
        "send_priority": 3,
        "receive_priority": 3
      },
      "current_stats": {
        "technology": "100.71",
        "infrastructure": "5,300.01",
        "strength": "22052.531"
      }
    },
    "645768": {
      "ruler_name": "Sitthemdown",
      "nation_name": "Emperor Protects",
      "discord_handle": "",
      "has_dra": false,
      "notes": "",
      "slots": {
        "sendTech": 0,
        "sendCash": 0,
        "getTech": 0,
        "getCash": 0,
        "send_priority": 3,
        "receive_priority": 3
      },
      "current_stats": {
        "technology": "200.61",
        "infrastructure": "5,000.09",
        "strength": "19169.377"
      }
    },
    "646307": {
      "ruler_name": "Hermes Observer",
      "nation_name": "Radchaai",
      "discord_handle": "",
      "has_dra": false,
      "notes": "",
      "slots": {
        "sendTech": 0,
        "sendCash": 0,
        "getTech": 0,
        "getCash": 0,
        "send_priority": 3,
        "receive_priority": 3
      },
      "current_stats": {
        "technology": "0.00",
        "infrastructure": "4,999.99",
        "strength": "18285.17"
      }
    },
    "646870": {
      "ruler_name": "Waffless",
      "nation_name": "Wafflandia",
      "discord_handle": "",
      "has_dra": false,
      "notes": "",
      "slots": {
        "sendTech": 0,
        "sendCash": 0,
        "getTech": 0,
        "getCash": 0,
        "send_priority": 3,
        "receive_priority": 3
      },
      "current_stats": {
        "technology": "32.20",
        "infrastructure": "2,602.67",
        "strength": "8803.982"
      }
    },
    "646947": {
      "ruler_name": "Hawggystyle",
      "nation_name": "Djibigbouti",
      "discord_handle": "",
      "has_dra": false,
      "notes": "",
      "slots": {
        "sendTech": 0,
        "sendCash": 0,
        "getTech": 0,
        "getCash": 0,
        "send_priority": 3,
        "receive_priority": 3
      },
      "current_stats": {
        "technology": "199.55",
        "infrastructure": "5,499.99",
        "strength": "21761.22"
      }
    },
    "646975": {
      "ruler_name": "Thomassh",
      "nation_name": "HighGateHaven",
      "discord_handle": "",
      "has_dra": false,
      "notes": "",
      "slots": {
        "sendTech": 0,
        "sendCash": 0,
        "getTech": 0,
        "getCash": 0,
        "send_priority": 3,
        "receive_priority": 3
      },
      "current_stats": {
        "technology": "108.86",
        "infrastructure": "4,999.99",
        "strength": "16581.872"
      }
    },
    "647449": {
      "ruler_name": "thelostsoul",
      "nation_name": "TheLostNation",
      "discord_handle": "",
      "has_dra": false,
      "notes": "",
      "slots": {
        "sendTech": 0,
        "sendCash": 0,
        "getTech": 0,
        "getCash": 0,
        "send_priority": 3,
        "receive_priority": 3
      },
      "current_stats": {
        "technology": "69.33",
        "infrastructure": "1,999.00",
        "strength": "7553.788"
      }
    },
    "647502": {
      "ruler_name": "twitchanswers",
      "nation_name": "Twitch",
      "discord_handle": "",
      "has_dra": false,
      "notes": "",
      "slots": {
        "sendTech": 0,
        "sendCash": 0,
        "getTech": 0,
        "getCash": 0,
        "send_priority": 3,
        "receive_priority": 3
      },
      "current_stats": {
        "technology": "129.99",
        "infrastructure": "1,598.86",
        "strength": "7509.336"
      }
    },
    "647787": {
      "ruler_name": "Rhys Osborne",
      "nation_name": "Scottish Rump State",
      "discord_handle": "",
      "has_dra": false,
      "notes": "",
      "slots": {
        "sendTech": 0,
        "sendCash": 0,
        "getTech": 0,
        "getCash": 0,
        "send_priority": 3,
        "receive_priority": 3
      },
      "current_stats": {
        "technology": "8.50",
        "infrastructure": "51.10",
        "strength": "348.186"
      }
    }
  }
}